opencv_table_plotter/__init__.py
opencv_table_plotter/main.py
opencv_table_plotter-0.1.dist-info/METADATA
opencv_table_plotter-0.1.dist-info/WHEEL
opencv_table_plotter-0.1.dist-info/top_level.txt
opencv_table_plotter-0.1.dist-info/RECORD
