Metadata-Version: 2.1
Name: opencv-table-plotter
Version: 0.1
